{
    "Animals": [
      { "name": "いぬ", "image": "dog.png", "audio": "dog.mp3" },
      { "name": "ねこ", "image": "cat.png", "audio": "cat.mp3" },
      { "name": "うま", "image": "horse.png", "audio": "horse.mp3" }
    ],
    "Numbers": [
      { "name": "いち", "image": "1.png", "audio": "1.mp3" },
      { "name": "に", "image": "2.png", "audio": "2.mp3" }
    ],
    "Countries": [
      { "name": "にほん", "image": "japan.png", "audio": "japan.mp3" }
    ],
    "Foods": [
      { "name": "すし", "image": "sushi.png", "audio": "sushi.mp3" }
    ]
  }
  